<?xml version="1.0" encoding="utf-8" standalone="yes"?>
<cleanup>
	<cups>
		<cup notnull="True" owner="43" cmcc="True">
			<items>
				<item notnull="True" cont="1073746033" inotnull="True" type="Gold" />
				<item notnull="False" inotnull="True" type="MelisandesHairDye" />
			</items>
		</cup>
		<cup notnull="True" owner="43461" cmcc="False">
			<items />
		</cup>
		<cup notnull="True" owner="45715" cmcc="True">
			<items>
				<item notnull="False" inotnull="True" type="Gold" />
			</items>
		</cup>
		<cup notnull="True" owner="42" cmcc="False">
			<items />
		</cup>
		<cup notnull="True" owner="1651" cmcc="True">
			<items>
				<item notnull="True" cont="1073755301" inotnull="True" type="Gold" />
				<item notnull="False" inotnull="True" type="IronOre" />
				<item notnull="False" inotnull="True" type="Static" />
				<item notnull="False" inotnull="True" type="Static" />
				<item notnull="False" inotnull="True" type="Static" />
				<item notnull="False" inotnull="True" type="Saltpeter" />
			</items>
		</cup>
		<cup notnull="True" owner="50205" cmcc="True">
			<items>
				<item notnull="True" cont="1074016915" inotnull="True" type="Gold" />
				<item notnull="False" inotnull="True" type="Static" />
				<item notnull="False" inotnull="True" type="Static" />
				<item notnull="False" inotnull="True" type="Static" />
				<item notnull="False" inotnull="True" type="Static" />
			</items>
		</cup>
		<cup notnull="True" owner="7201" cmcc="True">
			<items>
				<item notnull="False" inotnull="True" type="Gold" />
			</items>
		</cup>
		<cup notnull="True" owner="830" cmcc="False">
			<items>
				<item notnull="False" inotnull="True" type="Gold" />
				<item notnull="False" inotnull="True" type="Lockpick" />
				<item notnull="False" inotnull="True" type="Gold" />
			</items>
		</cup>
		<cup notnull="True" owner="48134" cmcc="False">
			<items>
				<item notnull="False" inotnull="True" type="Gold" />
			</items>
		</cup>
	</cups>
</cleanup>